gp_emulator/GaussianProcess.py
gp_emulator/__init__.py
gp_emulator/emulation_helpers.py
gp_emulator/lhd.py
gp_emulator/multivariate_gp.py
gp_emulator-1.6.10.dist-info/METADATA
gp_emulator-1.6.10.dist-info/RECORD
gp_emulator-1.6.10.dist-info/WHEEL
gp_emulator-1.6.10.dist-info/top_level.txt
