Metadata-Version: 2.1
Name: gp-emulator
Version: 1.6.10
Summary: A Python Gaussian Process emulator software package
Home-page: http://github.com/jgomezdans/gp_emulator
Author: J Gomez-Dans
Author-email: j.gomez-dans@ucl.ac.uk
License: UNKNOWN
Platform: UNKNOWN
Classifier: Development Status :: 4 - Beta
Classifier: Natural Language :: English
Classifier: Operating System :: OS Independent
Classifier: Programming Language :: Python :: 3
Classifier: Topic :: Scientific/Engineering
Classifier: Topic :: Software Development :: Libraries :: Python Modules
Classifier: Intended Audience :: Science/Research
Classifier: Intended Audience :: End Users/Desktop
Classifier: Intended Audience :: Developers
Classifier: Environment :: Console
Requires-Dist: numpy
Requires-Dist: scipy
